jinja2cli/__init__.py
jinja2cli/cli.py
jinja2_cli-1.0.0.dist-info/WHEEL
jinja2_cli-1.0.0.dist-info/entry_points.txt
jinja2_cli-1.0.0.dist-info/METADATA
jinja2_cli-1.0.0.dist-info/RECORD
