Metadata-Version: 2.3
Name: jinja2-cli
Version: 1.0.0
Summary: The CLI interface to Jinja2
Author: Matt Robenolt
Author-email: Matt Robenolt <m@robenolt.com>
License: Copyright (c) 2017-2026, Matt Robenolt
Classifier: Programming Language :: Python :: 3
Classifier: Programming Language :: Python :: 3 :: Only
Classifier: Programming Language :: Python :: 3.8
Classifier: Programming Language :: Python :: 3.9
Classifier: Programming Language :: Python :: 3.10
Classifier: Programming Language :: Python :: 3.11
Classifier: Programming Language :: Python :: 3.12
Classifier: License :: OSI Approved :: BSD License
Classifier: Operating System :: OS Independent
Requires-Dist: jinja2>=3.1
Requires-Dist: hjson ; extra == 'hjson'
Requires-Dist: json5 ; extra == 'json5'
Requires-Dist: tomli ; python_full_version < '3.11' and extra == 'toml'
Requires-Dist: xmltodict ; extra == 'xml'
Requires-Dist: pyyaml ; extra == 'yaml'
Requires-Python: >=3.8
Project-URL: Homepage, https://github.com/mattrobenolt/jinja2-cli
Project-URL: Issues, https://github.com/mattrobenolt/jinja2-cli/issues
Provides-Extra: hjson
Provides-Extra: json5
Provides-Extra: toml
Provides-Extra: xml
Provides-Extra: yaml
